{
"address":[
"ठेगाना"
],
"amenity/bank":[
"बैंक"
],
"amenity/bar":[
"बार"
],
"amenity/cafe":[
"क्याफे"
],
"amenity/fast_food":[
"फास्ट फूड"
],
"amenity/hospital":[
"अस्पताल मैदान"
],
"amenity/place_of_worship":[
"पूजा गर्ने ठाउँ"
],
"amenity/restaurant":[
"रेस्टुरेन्ट"
],
"area":[
"क्षेत्र"
],
"building/house":[
"घर"
],
"highway/street_lamp":[
"सडक बत्ति"
],
"leisure/park":[
"पार्क"
],
"line":[
"लाइन"
],
"place/city":[
"शहर"
],
"place/square":[
"वर्गाकार"
],
"point":[
"पोइन्ट"
],
"shop/supermarket":[
"सुपरमार्केट"
]
}
